LICENSE
README.md
setup.py
GrowattRequestsAsync.egg-info/PKG-INFO
GrowattRequestsAsync.egg-info/SOURCES.txt
GrowattRequestsAsync.egg-info/dependency_links.txt
GrowattRequestsAsync.egg-info/requires.txt
GrowattRequestsAsync.egg-info/top_level.txt
growattRequestsAsync/__init__.py
growattRequestsAsync/exceptions.py