Metadata-Version: 2.1
Name: GrowattRequestsAsync
Version: 1.0.0
Summary: Asynchronous API wrapper (client) for Growatt API which allows you to easily pull your data from Growatt servers.
Home-page: https://github.com/dwbruijn/GrowattRequestsAsync
Author: dwbruijn
License: UNKNOWN
Platform: UNKNOWN
Classifier: Programming Language :: Python :: 3
Classifier: License :: OSI Approved :: MIT License
Classifier: Operating System :: OS Independent
Requires-Python: >=3.7
License-File: LICENSE
